grrph/__init__.py
grrph/converter.py
grrph/distance.py
grrph/fast_wl.py
grrph/inductive_wl.py
grrph/kernel.py
grrph/util.py
grrph/connectors/outerplanarity.py
grrph/datasets/RIGIDDataset.py
grrph/sklearn/ensembling.py
grrph/sklearn/preprocessing.py
grrph-0.0.4.dist-info/LICENSE
grrph-0.0.4.dist-info/METADATA
grrph-0.0.4.dist-info/WHEEL
grrph-0.0.4.dist-info/top_level.txt
grrph-0.0.4.dist-info/RECORD
