Metadata-Version: 2.1
Name: grrph
Version: 0.0.4
Summary: grrph -- Pascals Python Graph Library 
Author-email: Pascal Welke <pascal.welke@tuwien.ac.at>
Project-URL: Homepage, https://github.com/pwelke/grrph
Project-URL: Issues, https://github.com/pwelke/grrph/issues
Classifier: Programming Language :: Python :: 3
Classifier: License :: OSI Approved :: MIT License
Classifier: Operating System :: OS Independent
Requires-Python: >=3.8
License-File: LICENSE
Requires-Dist: numpy
Requires-Dist: scipy
Requires-Dist: networkx
Requires-Dist: POT
